tpds/__init__.py
tpds/cert_tools/__init__.py
tpds/cert_tools/cert.py
tpds/cert_tools/cert_utils.py
tpds/cert_tools/ext_builder.py
tpds/cert_tools/sign_csr.py
tpds/cert_tools/timefix_backend.py
tpds_certificate_tools-1.2.0.dist-info/licenses/LICENSE
tpds_certificate_tools-1.2.0.dist-info/METADATA
tpds_certificate_tools-1.2.0.dist-info/WHEEL
tpds_certificate_tools-1.2.0.dist-info/entry_points.txt
tpds_certificate_tools-1.2.0.dist-info/top_level.txt
tpds_certificate_tools-1.2.0.dist-info/RECORD
