Metadata-Version: 2.4
Name: tpds-certificate-tools
Version: 1.2.0
Summary: Microchip(SPG) Trust Platform Certificate Utilities
Maintainer-email: Microchip Technology <SPG.Tools@microchip.com>
License: (c) 2018-2023 Microchip Technology Inc. and its subsidiaries.
Classifier: License :: Other/Proprietary License
Classifier: Development Status :: 4 - Beta
Classifier: Programming Language :: Python :: 3
Classifier: Operating System :: OS Independent
Requires-Python: >=3.8
License-File: LICENSE
Requires-Dist: asn1crypto
Requires-Dist: cryptography~=35.0.0
Requires-Dist: pyOpenSSL~=22.0.0
Requires-Dist: bitstring
Provides-Extra: dev
Requires-Dist: flake8; extra == "dev"
Requires-Dist: black; extra == "dev"
Requires-Dist: isort; extra == "dev"
Requires-Dist: mypy; extra == "dev"
Provides-Extra: test
Requires-Dist: pytest-cov; extra == "test"
Dynamic: license-file
